a1_notation/__init__.py
a1_notation/column_lookup.py
a1_notation/py.typed
a1_notation-0.1.dev4.dist-info/METADATA
a1_notation-0.1.dev4.dist-info/WHEEL
a1_notation-0.1.dev4.dist-info/licenses/LICENSE
a1_notation-0.1.dev4.dist-info/RECORD
