Metadata-Version: 2.1
Name: a1_notation
Version: 0.1.dev4
Summary: A1 Notation lookups in various formats for pre-computed or generated-as-needed usage
Project-URL: Homepage, https://github.com/brooketalcott/a1_notation
Project-URL: Repository, https://github.com/brooketalcott/a1_notation
Project-URL: Issue-Tracker, https://github.com/brooketalcott/a1_notation/issues
Author: Brooke Talcott
License: MIT License
License-File: LICENSE
Keywords: a1 notation,excel
Classifier: Development Status :: 1 - Planning
Classifier: Intended Audience :: Developers
Classifier: License :: OSI Approved :: MIT License
Classifier: Operating System :: OS Independent
Classifier: Programming Language :: Python :: 3.11
Classifier: Topic :: Utilities
Requires-Python: >=3.11
Provides-Extra: dev
Requires-Dist: black>=23.3.0; extra == 'dev'
Requires-Dist: hatch-vcs>=0.3.0; extra == 'dev'
Requires-Dist: pre-commit>=3.3.3; extra == 'dev'
Requires-Dist: ruff>=0.0.277; extra == 'dev'
